leaspy/__init__.py
leaspy/algo/__init__.py
leaspy/algo/algo_with_annealing.py
leaspy/algo/algo_with_device.py
leaspy/algo/algo_with_samplers.py
leaspy/algo/base.py
leaspy/algo/data/default_constant_prediction.json
leaspy/algo/data/default_lme_fit.json
leaspy/algo/data/default_lme_personalize.json
leaspy/algo/data/default_mcmc_saem.json
leaspy/algo/data/default_mean_posterior.json
leaspy/algo/data/default_mode_posterior.json
leaspy/algo/data/default_scipy_minimize.json
leaspy/algo/data/default_simulate.json
leaspy/algo/fit/__init__.py
leaspy/algo/fit/base.py
leaspy/algo/fit/fit_output_manager.py
leaspy/algo/fit/lme_fit.py
leaspy/algo/fit/mcmc_saem.py
leaspy/algo/personalize/__init__.py
leaspy/algo/personalize/base.py
leaspy/algo/personalize/constant_prediction_algo.py
leaspy/algo/personalize/lme_personalize.py
leaspy/algo/personalize/mcmc.py
leaspy/algo/personalize/mean_posterior.py
leaspy/algo/personalize/mode_posterior.py
leaspy/algo/personalize/scipy_minimize.py
leaspy/algo/settings.py
leaspy/algo/simulate/__init__.py
leaspy/algo/simulate/base.py
leaspy/algo/simulate/simulate.py
leaspy/constants.py
leaspy/datasets/__init__.py
leaspy/datasets/data/alzheimer.csv
leaspy/datasets/data/parkinson-putamen-train_and_test.csv
leaspy/datasets/data/parkinson-putamen.csv
leaspy/datasets/data/parkinson.csv
leaspy/datasets/data/simulated_data_for_joint.csv
leaspy/datasets/data/simulated_data_for_mixture.csv
leaspy/datasets/individual_parameters/alzheimer-individual_parameters.csv
leaspy/datasets/individual_parameters/parkinson-individual_parameters.csv
leaspy/datasets/individual_parameters/parkinson-putamen-individual_parameters.csv
leaspy/datasets/loader.py
leaspy/datasets/model_parameters/alzheimer-model_parameters.json
leaspy/datasets/model_parameters/parkinson-model_parameters.json
leaspy/datasets/model_parameters/parkinson-putamen-model_parameters.json
leaspy/exceptions.py
leaspy/io/__init__.py
leaspy/io/data/__init__.py
leaspy/io/data/abstract_dataframe_data_reader.py
leaspy-2.0.2.dist-info/METADATA
leaspy-2.0.2.dist-info/WHEEL
leaspy-2.0.2.dist-info/licenses/LICENSE
leaspy-2.0.2.dist-info/RECORD
