Metadata-Version: 2.4
Name: leaspy
Version: 2.0.2
Summary: Leaspy is a software package for the statistical analysis of longitudinal data.
License-Expression: BSD-3-Clause-Clear
License-File: LICENSE
Keywords: leaspy,longitudinal,mixed-model
Author: AramisLab Research Team
Maintainer: Nicolas Gensollen
Maintainer-email: nicolas.gensollen@inria.fr
Requires-Python: >=3.9,<=3.13
Classifier: Development Status :: 4 - Beta
Classifier: Intended Audience :: Developers
Classifier: Intended Audience :: Science/Research
Classifier: License :: OSI Approved :: BSD License
Classifier: Operating System :: OS Independent
Classifier: Programming Language :: Python :: 3.9
Classifier: Programming Language :: Python :: 3.10
Classifier: Programming Language :: Python :: 3.11
Classifier: Programming Language :: Python :: 3.12
Classifier: Programming Language :: Python :: 3.13
Requires-Dist: joblib (>=1.2.0)
Requires-Dist: lifelines (>=0.27.4)
Requires-Dist: matplotlib (>=3.6.3,<4)
Requires-Dist: numpy (>=1.26.4,<2)
Requires-Dist: pandas (>=2.2.2,<3)
Requires-Dist: scikit-learn (>=1.2.2,<2)
Requires-Dist: scipy (>=1.13.1)
Requires-Dist: statsmodels (>=0.13.5,<1)
Requires-Dist: torch (>=2.2.0,<2.8)
Project-URL: Documentation, https://leaspy.readthedocs.io
Project-URL: Homepage, https://leaspy.readthedocs.io
Project-URL: issues, https://github.com/aramis-lab/leaspy/issues
Project-URL: sources, https://github.com/aramis-lab/leaspy
